README.md
setup.py
pulumi_wordle/__init__.py
pulumi_wordle/_utilities.py
pulumi_wordle/provider.py
pulumi_wordle/pulumi-plugin.json
pulumi_wordle/py.typed
pulumi_wordle/wordle.py
pulumi_wordle.egg-info/PKG-INFO
pulumi_wordle.egg-info/SOURCES.txt
pulumi_wordle.egg-info/dependency_links.txt
pulumi_wordle.egg-info/not-zip-safe
pulumi_wordle.egg-info/requires.txt
pulumi_wordle.egg-info/top_level.txt