Metadata-Version: 2.1
Name: pulumi-wordle
Version: 0.2.3a1656433444
Summary: Stand up Wordle while you stand up infrastructure
Home-page: https://github.com/aaronfriel/pulumi-wordle
License: Apache-2.0
Project-URL: Repository, https://github.com/aaronfriel/pulumi-wordle
Keywords: pulumi wordle category/Fun category/Utility
Platform: UNKNOWN
